README.md
setup.py
simpdatastructs/__init__.py
simpdatastructs.egg-info/PKG-INFO
simpdatastructs.egg-info/SOURCES.txt
simpdatastructs.egg-info/dependency_links.txt
simpdatastructs.egg-info/top_level.txt
simpdatastructs/base/__init__.py
simpdatastructs/base/utility_fxns.py
simpdatastructs/bidict/__init__.py
simpdatastructs/bidict/bidict.py
simpdatastructs/bidict/bidict_mult.py