Metadata-Version: 2.1
Name: simpdatastructs
Version: 0.1.1
Summary: Simple Data Structures
Home-page: https://github.com/StephenMal/simpdatastructs
Author: Stephen Maldonado
Author-email: simpdatastructs@stephenmal.com
License: UNKNOWN
Platform: UNKNOWN
Classifier: Development Status :: 1 - Planning
Classifier: Programming Language :: Python :: 3 :: Only
Classifier: Topic :: Utilities
